macedon/__init__.py
macedon/__main__.py
macedon/_common.py
macedon/_version.py
macedon/entrypoint.py
macedon/fileparser.py
macedon/io.py
macedon/logger.py
macedon/printer.py
macedon/synchronizer.py
macedon/worker.py
macedon-0.13.0.dist-info/METADATA
macedon-0.13.0.dist-info/WHEEL
macedon-0.13.0.dist-info/entry_points.txt
macedon-0.13.0.dist-info/licenses/LICENSE
macedon-0.13.0.dist-info/RECORD
