Metadata-Version: 2.3
Name: macedon
Version: 0.13.0
Summary: CLI web service availability verifier
Project-URL: Homepage, https://github.com/es7s/macedon
Author-email: Aleksandr Shavykin <0.delameter@gmail.com>
License: MIT
License-File: LICENSE
Keywords: check,cli,console,healthcheck,http,https,request,socks,terminal,web,web-service
Classifier: Development Status :: 3 - Alpha
Classifier: Environment :: Console
Classifier: Intended Audience :: Developers
Classifier: Intended Audience :: System Administrators
Classifier: License :: OSI Approved :: MIT License
Classifier: Operating System :: POSIX :: Linux
Classifier: Programming Language :: Python
Classifier: Programming Language :: Python :: 3
Classifier: Programming Language :: Python :: 3.10
Classifier: Topic :: Terminals
Requires-Python: >=3.10
Requires-Dist: click~=8.1.3
Requires-Dist: es7s-commons~=1.3.1
Requires-Dist: psutil~=5.9.4
Requires-Dist: pytermor~=2.106.6.dev0
Requires-Dist: requests~=2.28.2
Provides-Extra: socks
Requires-Dist: requests[socks]; extra == 'socks'
